mst/authsrv/__init__.py
mst/authsrv/authsrv.py
mst_authsrv-1.3.0.dist-info/METADATA
mst_authsrv-1.3.0.dist-info/WHEEL
mst_authsrv-1.3.0.dist-info/top_level.txt
mst_authsrv-1.3.0.dist-info/RECORD
