Metadata-Version: 2.4
Name: mst-authsrv
Version: 1.3.0
Summary: An interface for authsrv
Author-email: Missouri University of Science and Technology - Information Technology <it-ai@mst.edu>
Requires-Python: >=3.8
Requires-Dist: mst-core
Requires-Dist: cachetools
